License.txt
pyproject.toml
setup.py
Caculator/Caculator.py
Caculator/__init__.py
HongboCalc.egg-info/PKG-INFO
HongboCalc.egg-info/SOURCES.txt
HongboCalc.egg-info/dependency_links.txt
HongboCalc.egg-info/top_level.txt