Metadata-Version: 2.1
Name: HongboCalc
Version: 0.0.1
Summary: Makes super calculation
Home-page: UNKNOWN
Author: HB
Author-email: hb@gmail.com
License: MIT
Platform: UNKNOWN
License-File: License.txt
